azure/template/__init__.py
azure/template/_version.py
azure/template/template_code.py
azure_template-0.0.18.dist-info/METADATA
azure_template-0.0.18.dist-info/WHEEL
azure_template-0.0.18.dist-info/top_level.txt
azure_template-0.0.18.dist-info/RECORD
